[
  {
    "img": "/products/layer-hoodie-black.png",
    "title": "LAYER Oversized Hoodie",
    "description": "Oversized hoodie made from premium cotton. Clean silhouette with a minimal LAYER logo, designed for everyday wear.",
    "defaultPrice": 129,
    "discountPrice": 99,
    "discountPercent": 23,
    "rating": 4.8,
    "categories": ["hoodies", "streetwear", "unisex"],
    "color": "white",
    "hasDiscount": true,
    "isNewProduct": false,
    "quantity": 100
  },
  {
    "img": "/products/layer-tshirt-essential.png",
    "title": "Essential T-Shirt",
    "description": "Minimalist everyday t-shirt crafted from soft heavyweight cotton with a relaxed fit.",
    "defaultPrice": 49,
    "discountPrice": 39,
    "discountPercent": 20,
    "rating": 4.6,
    "categories": ["t-shirts", "basics", "streetwear"],
    "color": "black",
    "hasDiscount": true,
    "isNewProduct": false,
    "quantity": 50
  },
  {
    "img": "/products/layer-jacket-utility.png",
    "title": "Utility Jacket",
    "description": "Functional streetwear jacket with multiple pockets and a structured fit. Built for urban movement.",
    "defaultPrice": 199,
    "discountPrice": 159,
    "discountPercent": 20,
    "rating": 4.9,
    "categories": ["jackets", "outerwear", "streetwear"],
    "color": "white",
    "hasDiscount": true,
    "isNewProduct": false,
    "quantity": 30
  },
  {
    "img": "/products/layer-pants-cargo.png",
    "title": "Cargo Pants",
    "description": "Relaxed fit cargo pants with adjustable cuffs and utility pockets. Durable and comfortable.",
    "defaultPrice": 149,
    "discountPrice": 119,
    "discountPercent": 20,
    "rating": 4.7,
    "categories": ["pants", "cargo", "streetwear"],
    "color": "white",
    "hasDiscount": true,
    "isNewProduct": false,
    "quantity": 40
  },
  {
    "img": "/products/layer-sweatshirt-grey.png",
    "title": "Minimal Sweatshirt",
    "description": "Clean crewneck sweatshirt with a soft brushed interior. Designed for layering.",
    "defaultPrice": 99,
    "discountPrice": 79,
    "discountPercent": 20,
    "rating": 4.5,
    "categories": ["sweatshirts", "basics", "streetwear"],
    "color": "grey",
    "hasDiscount": true,
    "isNewProduct": false,
    "quantity": 12
  },
  {
    "img": "/products/layer-cap-black.png",
    "title": "Logo Cap",
    "description": "Structured cap with embroidered LAYER logo. Adjustable strap for a perfect fit.",
    "defaultPrice": 39,
    "discountPrice": 29,
    "discountPercent": 26,
    "rating": 4.4,
    "categories": ["accessories", "headwear", "streetwear"],
    "color": "black",
    "hasDiscount": true,
    "isNewProduct": false,
    "quantity": 25
  },
  {
    "img": "/products/layer-bomber-jacket.png",
    "title": "Bomber Jacket",
    "description": "Modern bomber jacket with a clean silhouette and lightweight insulation for everyday use.",
    "defaultPrice": 179,
    "discountPrice": 139,
    "discountPercent": 22,
    "rating": 4.8,
    "categories": ["jackets", "outerwear", "streetwear"],
    "color": "white",
    "hasDiscount": true,
    "isNewProduct": false,
    "quantity": 20
  },
  {
    "img": "/products/layer-long-sleeve.png",
    "title": "Long Sleeve Tee",
    "description": "Relaxed long sleeve t-shirt made from premium cotton. Perfect for transitional seasons.",
    "defaultPrice": 69,
    "discountPrice": 55,
    "discountPercent": 20,
    "rating": 4.6,
    "categories": ["t-shirts", "longsleeve", "streetwear"],
    "color": "grey",
    "hasDiscount": true,
    "isNewProduct": false,
    "quantity": 0
  },
  {
    "img": "/products/layer-beanie.png",
    "title": "Essential Beanie",
    "description": "Minimal beanie with a snug fit and subtle branding. Designed for everyday comfort.",
    "defaultPrice": 29,
    "discountPrice": 22,
    "discountPercent": 24,
    "rating": 4.3,
    "categories": ["accessories", "beanies", "streetwear"],
    "color": "grey",
    "hasDiscount": true,
    "isNewProduct": false,
    "quantity": 15
  },
  {
    "img": "/products/layer-track-pants.png",
    "title": "Track Pants",
    "description": "Relaxed track pants with elastic waistband and tapered legs. Clean design with functional comfort.",
    "defaultPrice": 119,
    "discountPrice": 95,
    "discountPercent": 20,
    "rating": 4.7,
    "categories": ["pants", "track", "streetwear"],
    "color": "white",
    "hasDiscount": true,
    "isNewProduct": false,
    "quantity": 10
  },
  {
    "img": "/products/layer-heavyweight-box-tee.png",
    "title": "Heavyweight Box Tee",
    "description": "Boxy fit t-shirt made from dense heavyweight cotton with dropped shoulders and a clean neckline.",
    "defaultPrice": 59,
    "discountPrice": 59,
    "discountPercent": 0,
    "rating": 4.7,
    "categories": ["t-shirts", "basics", "streetwear"],
    "color": "charcoal",
    "hasDiscount": false,
    "isNewProduct": true,
    "quantity": 34
  },
  {
    "img": "/products/layer-washed-zip-hoodie.png",
    "title": "Washed Zip Hoodie",
    "description": "Relaxed zip hoodie with a vintage wash, double-layer hood and subtle tonal LAYER embroidery.",
    "defaultPrice": 139,
    "discountPrice": 139,
    "discountPercent": 0,
    "rating": 4.9,
    "categories": ["hoodies", "streetwear", "unisex"],
    "color": "washed black",
    "hasDiscount": false,
    "isNewProduct": true,
    "quantity": 18
  },
  {
    "img": "/products/layer-coach-jacket.png",
    "title": "City Coach Jacket",
    "description": "Lightweight coach jacket with snap buttons, a drawcord hem and a water-resistant outer shell.",
    "defaultPrice": 169,
    "discountPrice": 169,
    "discountPercent": 0,
    "rating": 4.6,
    "categories": ["jackets", "outerwear", "streetwear"],
    "color": "navy",
    "hasDiscount": false,
    "isNewProduct": false,
    "quantity": 22
  },
  {
    "img": "/products/layer-carpenter-pants.png",
    "title": "Carpenter Pants",
    "description": "Loose carpenter pants in durable cotton canvas with reinforced knees and functional utility loops.",
    "defaultPrice": 145,
    "discountPrice": 145,
    "discountPercent": 0,
    "rating": 4.8,
    "categories": ["pants", "cargo", "streetwear"],
    "color": "sand",
    "hasDiscount": false,
    "isNewProduct": true,
    "quantity": 27
  },
  {
    "img": "/products/layer-nylon-windbreaker.png",
    "title": "Nylon Windbreaker",
    "description": "Packable windbreaker with a high collar, mesh lining and adjustable cuffs for unpredictable city weather.",
    "defaultPrice": 159,
    "discountPrice": 159,
    "discountPercent": 0,
    "rating": 4.5,
    "categories": ["jackets", "outerwear", "streetwear"],
    "color": "olive",
    "hasDiscount": false,
    "isNewProduct": false,
    "quantity": 16
  },
  {
    "img": "/products/layer-crossbody-utility-bag.png",
    "title": "Crossbody Utility Bag",
    "description": "Compact crossbody bag with multiple zip compartments and an adjustable webbing strap for daily essentials.",
    "defaultPrice": 65,
    "discountPrice": 65,
    "discountPercent": 0,
    "rating": 4.4,
    "categories": ["accessories", "streetwear", "unisex"],
    "color": "black",
    "hasDiscount": false,
    "isNewProduct": true,
    "quantity": 41
  },
  {
    "img": "/products/layer-five-panel-cap.png",
    "title": "Five Panel Cap",
    "description": "Low-profile five panel cap made from lightweight ripstop fabric with reflective logo detailing.",
    "defaultPrice": 45,
    "discountPrice": 45,
    "discountPercent": 0,
    "rating": 4.3,
    "categories": ["accessories", "headwear", "streetwear"],
    "color": "burgundy",
    "hasDiscount": false,
    "isNewProduct": false,
    "quantity": 29
  },
  {
    "img": "/products/layer-ribbed-longsleeve.png",
    "title": "Ribbed Longsleeve",
    "description": "Fitted ribbed longsleeve with extended cuffs and a minimal woven label at the side seam.",
    "defaultPrice": 75,
    "discountPrice": 75,
    "discountPercent": 0,
    "rating": 4.6,
    "categories": ["t-shirts", "longsleeve", "basics"],
    "color": "cream",
    "hasDiscount": false,
    "isNewProduct": true,
    "quantity": 36
  },
  {
    "img": "/products/layer-wide-leg-sweatpants.png",
    "title": "Wide Leg Sweatpants",
    "description": "Heavyweight fleece sweatpants with a wide leg silhouette, deep pockets and an adjustable waistband.",
    "defaultPrice": 125,
    "discountPrice": 125,
    "discountPercent": 0,
    "rating": 4.8,
    "categories": ["pants", "track", "streetwear"],
    "color": "heather grey",
    "hasDiscount": false,
    "isNewProduct": true,
    "quantity": 24
  },
  {
    "img": "/products/layer-canvas-overshirt.png",
    "title": "Canvas Overshirt",
    "description": "Structured canvas overshirt with oversized patch pockets, metal buttons and a relaxed layering fit.",
    "defaultPrice": 149,
    "discountPrice": 149,
    "discountPercent": 0,
    "rating": 4.7,
    "categories": ["jackets", "outerwear", "streetwear"],
    "color": "dark brown",
    "hasDiscount": false,
    "isNewProduct": false,
    "quantity": 13
  }
]
